mils_de/__init__.py
mils_de/data.py
mils_de/estimator.py
mils_de/metrics.py
mils_de/regressor.py
mils_de/utils.py
mils_de/weights.py
mils_de/geometry/__init__.py
mils_de/geometry/constraints.py
mils_de/geometry/distribution.py
mils_de/geometry/params.py
mils_de/geometry/synthetic.py
mils_de-1.0.dist-info/licenses/LICENSE
mils_de-1.0.dist-info/METADATA
mils_de-1.0.dist-info/WHEEL
mils_de-1.0.dist-info/top_level.txt
mils_de-1.0.dist-info/RECORD
