Metadata-Version: 2.4
Name: mils_de
Version: 1.0
Summary: The mils-de package implements the the DensityEstimator model used to predict the Plasma density given the Power and Phase of possibly multiple MILS recivers.
Author-email: Piero Coronica <piero.coronica@mpcdf.mpg.de>
License-Expression: MIT
Keywords: MILS,DensityEstimator
Classifier: Programming Language :: Python :: 3
Classifier: Operating System :: OS Independent
Requires-Python: >=3.10
License-File: LICENSE
Requires-Dist: pandas>=2.1
Requires-Dist: numpy>=1.20
Requires-Dist: scikit-learn>=1.3
Provides-Extra: full
Requires-Dist: optuna>=3.6; extra == "full"
Requires-Dist: matplotlib>=3.8; extra == "full"
Requires-Dist: ipykernel; extra == "full"
Provides-Extra: dynamic
Requires-Dist: version; extra == "dynamic"
Dynamic: license-file
